MANIFEST.in
README.md
requirements.txt
setup.py
test-requirements.txt
pyresty/__init__.py
pyresty/executable.py
pyresty/globals.py
pyresty/request.py
pyresty/utils.py
pyresty.egg-info/PKG-INFO
pyresty.egg-info/SOURCES.txt
pyresty.egg-info/dependency_links.txt
pyresty.egg-info/entry_points.txt
pyresty.egg-info/not-zip-safe
pyresty.egg-info/requires.txt
pyresty.egg-info/top_level.txt