Metadata-Version: 1.1
Name: pyresty
Version: 0.0.4
Summary: Python curl wrapper inspired by micha/resty
Home-page: https://github.com/roaet/pyresty
Author: Justin Hammond
Author-email: justin@roaet.com
License: Apache Software License
Keywords: resty curl
Platform: UNKNOWN
Classifier: Development Status :: 4 - Beta
Classifier: License :: OSI Approved :: Apache Software License
Classifier: Operating System :: POSIX :: Linux
Classifier: Programming Language :: Python :: 2.7
